vexilla_client/__init__.py
vexilla_client/client.py
vexilla_client/hasher.py
vexilla_client-0.0.1.dist-info/LICENSE
vexilla_client-0.0.1.dist-info/METADATA
vexilla_client-0.0.1.dist-info/WHEEL
vexilla_client-0.0.1.dist-info/top_level.txt
vexilla_client-0.0.1.dist-info/RECORD
