Metadata-Version: 2.1
Name: vexilla-client
Version: 0.0.1
Summary: A client for the Vexilla feature flag system
Home-page: https://github.com/vexilla/client-python
Author: cmgriffing
Author-email: cmgriffing@gmail.com
License: UNKNOWN
Platform: UNKNOWN
Classifier: Programming Language :: Python :: 3
Classifier: License :: OSI Approved :: MIT License
Classifier: Operating System :: OS Independent
Requires-Python: >=3.6
